AUTHORS
LICENSE
MANIFEST.in
README
README.rst
requirements.txt
setup.py
djhipchat/__init__.py
djhipchat/logger.py
djhipchat/models.py
djhipchat/tasks.py
djhipchat/tests.py
djhipchat/views.py
djhipchat/backends/__init__.py
djhipchat/backends/base.py
djhipchat/backends/celery.py
djhipchat/backends/dummy.py
djhipchat/backends/locmem.py
djhipchat/backends/request.py
djhipchat/management/__init__.py
djhipchat/management/commands/__init__.py
djhipchat/management/commands/hipchat.py
djhipchat2.egg-info/PKG-INFO
djhipchat2.egg-info/SOURCES.txt
djhipchat2.egg-info/dependency_links.txt
djhipchat2.egg-info/top_level.txt