Metadata-Version: 1.0
Name: djhipchat2
Version: 0.5.1
Summary: The most complete and configurable HipChat library for Django.
Home-page: https://github.com/paulcwatts/djhipchat2
Author: Paul Watts
Author-email: paulcwatts@gmail.com
License: BSD
Platform: UNKNOWN
Classifier: Environment :: Web Environment
Classifier: Framework :: Django
Classifier: Intended Audience :: Developers
Classifier: License :: OSI Approved :: BSD License
Classifier: Operating System :: OS Independent
Classifier: Programming Language :: Python :: 2.7
